wemulate/__init__.py
wemulate/controllers/__init__.py
wemulate/controllers/add_controller.py
wemulate/controllers/common.py
wemulate/controllers/config_controller.py
wemulate/controllers/delete_controller.py
wemulate/controllers/reset_controller.py
wemulate/controllers/restore_controller.py
wemulate/controllers/set_controller.py
wemulate/controllers/show_controller.py
wemulate/core/__init__.py
wemulate/core/database/__init__.py
wemulate/core/database/decorators.py
wemulate/core/database/models.py
wemulate/core/database/session.py
wemulate/core/database/setup.py
wemulate/core/database/utils.py
wemulate/core/exc.py
wemulate/core/version.py
wemulate/ext/__init__.py
wemulate/ext/settings/__init__.py
wemulate/ext/settings/config.py
wemulate/ext/settings/device.py
wemulate/ext/settings/folder.py
wemulate/ext/utils/__init__.py
wemulate/ext/utils/add.py
wemulate/ext/utils/common.py
wemulate/ext/utils/delete.py
wemulate/ext/utils/reset.py
wemulate/ext/utils/restore.py
wemulate/ext/utils/retrieve.py
wemulate/ext/utils/set.py
wemulate/main.py
wemulate/plugins/__init__.py
wemulate/templates/__init__.py
wemulate/templates/show_connection.jinja2
wemulate/utils/__init__.py
wemulate/utils/output.py
wemulate/utils/rendering.py
wemulate/utils/tcconfig.py
wemulate-2.0.5.dist-info/LICENSE
wemulate-2.0.5.dist-info/METADATA
wemulate-2.0.5.dist-info/WHEEL
wemulate-2.0.5.dist-info/entry_points.txt
wemulate-2.0.5.dist-info/RECORD
