Metadata-Version: 2.3
Name: wemulate
Version: 2.0.5
Summary: A modern WAN Emulator
License: GNU General Public License v3.0
Author: Julian Klaiber
Author-email: julian.klaiber@ost.ch
Requires-Python: >=3.8,<4.0
Classifier: License :: Other/Proprietary License
Classifier: Programming Language :: Python :: 3
Classifier: Programming Language :: Python :: 3.8
Classifier: Programming Language :: Python :: 3.9
Classifier: Programming Language :: Python :: 3.10
Classifier: Programming Language :: Python :: 3.11
Classifier: Programming Language :: Python :: 3.12
Classifier: Programming Language :: Python :: 3.13
Requires-Dist: SQLAlchemy (==1.4.3)
Requires-Dist: colorlog (==6.6.0)
Requires-Dist: jinja2 (==3.1.2)
Requires-Dist: mkdocs (>=1.4.2,<2.0.0)
Requires-Dist: mkdocs-material (>=9.0.5,<10.0.0)
Requires-Dist: mkdocstrings[python] (>=0.19.1,<0.20.0)
Requires-Dist: netifaces (==0.11.0)
Requires-Dist: pymdown-extensions (>=9.9.1,<10.0.0)
Requires-Dist: pyroute2 (==0.7.1)
Requires-Dist: pyyaml (==6.0.1)
Requires-Dist: rich (>=12.5.1,<13.0.0)
Requires-Dist: tcconfig (==0.27.1)
Requires-Dist: typer (==0.6.1)
Project-URL: Documentation, https://wemulate.github.io/wemulate
Project-URL: Homepage, https://wemulate.github.io/wemulate
Project-URL: Repository, https://github.io/wemulate/wemulate
